lapa/__init__.py
lapa/cluster.py
lapa/correction.py
lapa/count.py
lapa/genomic_regions.py
lapa/lapa.py
lapa/link.py
lapa/main.py
lapa/read.py
lapa/replication.py
lapa/result.py
lapa/talon.py
lapa/utils/__init__.py
lapa/utils/common.py
lapa/utils/gtf.py
lapa/utils/io.py
lapa-0.0.5.dist-info/METADATA
lapa-0.0.5.dist-info/WHEEL
lapa-0.0.5.dist-info/entry_points.txt
lapa-0.0.5.dist-info/top_level.txt
lapa-0.0.5.dist-info/RECORD
