Metadata-Version: 2.1
Name: lapa
Version: 0.0.5
Summary: Tools for alternative polyadenylation detection and analysis from diverse data sources (3'seq and long-reads) and transcript start site detection and analysis from long-read RNA-seq.
Home-page: https://github.com/mortazavilab/lapa
Author: M. Hasan Çelik
Author-email: muhammedhasancelik@gmail.com
License: MIT license
Keywords: genomics,long read RNA-seq,APA
Platform: UNKNOWN
Classifier: Natural Language :: English
Classifier: Programming Language :: Python :: 3.6
Classifier: Programming Language :: Python :: 3.7
Classifier: Programming Language :: Python :: 3.8
Classifier: Programming Language :: Python :: 3.9
Requires-Dist: setuptools
Requires-Dist: tqdm
Requires-Dist: numpy (<=1.23)
Requires-Dist: click
Requires-Dist: pandas
Requires-Dist: pybigwig
Requires-Dist: scipy
Requires-Dist: bamread (>=0.0.10)
Requires-Dist: pyranges (>=0.0.71)
Requires-Dist: sorted-nearest (==0.0.33)
Requires-Dist: kipoiseq (>=0.3.0)
Requires-Dist: matplotlib
Requires-Dist: betabinomial
